{
    "id": "block-feature-grid-lush-feature-grid-2",
    "name": "ugb/feature-grid",
    "attributes": {
        "design": "horizontal",
        "columns": 2,
        "borderRadius": 0,
        "shadow": 0,
        "columnBackgroundColor": "#e4e4d3",
        "columnBackgroundColor2": "#cdeac6",
        "imageWidth": 330,
        "imageHeight": 0,
        "imageTabletWidth": 150,
        "imageShadow": 0,
        "imageShapeStretch": true,
        "imageShapeFlipX": true,
        "imageShapeFlipY": true,
        "image1Id": 46,
        "image2Id": 49,
        "image1Url": "https://stackable-files.pages.dev/library/block-feature-grid-lush-feature-grid-2/image-1-url.jpg",
        "image2Url": "https://stackable-files.pages.dev/library/block-feature-grid-lush-feature-grid-2/image-2-url.jpg",
        "image1Alt": "FEATURE GRID 1",
        "image2Alt": "FEATURE GRID 2",
        "title1": "Feature Grid 1",
        "title2": "Feature Grid 2",
        "title3": "",
        "title4": "",
        "titleFontWeight": "300",
        "titleFontSize": 30,
        "titleTabletFontSize": 20,
        "titleColor": "#66826b",
        "description1": "Description for this block. You can use this space for describing your block.Description for this block. You can use this space for describing your block.",
        "description2": "Description for this block. You can use this space for describing your block.Description for this block. You can use this space for describing your block.",
        "description3": "",
        "description4": "",
        "descriptionFontSize": 14,
        "descriptionTabletFontSize": 14,
        "descriptionColor": "#000000",
        "showButton": false,
        "buttonDesign": "ghost",
        "buttonSize": "small",
        "buttonBackgroundColor": "#fcb900",
        "buttonBorderRadius": 0,
        "button1Text": "",
        "button1NewTab": false,
        "button2Text": "",
        "button2NewTab": false,
        "button3Text": "",
        "button3NewTab": false,
        "button4Text": "",
        "button4NewTab": false,
        "titleBottomMargin": 1,
        "marginUnit": "%",
        "paddingUnit": "%",
        "blockWidthUnit": "%",
        "align": "wide",
        "showTopSeparator": false,
        "topSeparatorDesign": "slant-1",
        "topSeparatorShadow": false,
        "showTopSeparatorLayer2": true,
        "showTopSeparatorLayer3": true,
        "blockTitle": "",
        "blockDescription": "",
        "contentAlign": "left"
    }
}