{
    "id": "block-pricing-box-yule-pricing-box",
    "name": "ugb/pricing-box",
    "attributes": {
        "columns": 3,
        "borderRadius": 6,
        "shadow": 5,
        "columnBackgroundColor": "#013e36",
        "columnBorderType": "solid",
        "columnBorderColor": "#02332c",
        "image1Id": 637,
        "image2Id": 639,
        "image3Id": 638,
        "image1Url": "https://stackable-files.pages.dev/library/block-pricing-box-yule-pricing-box/image-1-url.jpg",
        "image2Url": "https://stackable-files.pages.dev/library/block-pricing-box-yule-pricing-box/image-2-url.jpg",
        "image3Url": "https://stackable-files.pages.dev/library/block-pricing-box-yule-pricing-box/image-3-url.jpg",
        "image1Alt": "GIFT WRAPPING 1",
        "image2Alt": "Gift Wrapping 2",
        "image3Alt": "GIFT WRAPPING 3",
        "title1": "GIFT WRAPPING 1",
        "title2": "Gift Wrapping 2",
        "title3": "GIFT WRAPPING 3",
        "titleTag": "h6",
        "price2": "18",
        "price3": "27",
        "priceFontFamily": "DM Serif Text",
        "subPrice1": "<span class=\"ugb-highlight\"><strong>WITH FREE GIFT TAGS</strong></span>",
        "subPrice2": "<strong><span class=\"ugb-highlight\">EXCLUSIVE CHRISTMAS DEAL</span></strong>",
        "subPrice3": "<strong><span class=\"ugb-highlight\">WITH FREE GIFT TAGS</span></strong>",
        "buttonFontFamily": "sour",
        "buttonFontSize": 18,
        "buttonTextColor": "var(--stk-global-color-40036, #00473d)",
        "buttonBackgroundColor": "var(--stk-global-color-59238, #dab811)",
        "buttonHoverBackgroundColor": "#013029",
        "button1Text": "Buy now",
        "button1NewTab": false,
        "button2Text": "Buy now",
        "button2NewTab": false,
        "button3Text": "Buy now",
        "button3NewTab": false,
        "hoverEffect": "lift-shadow",
        "marginTop": 0,
        "paddingTop": 0,
        "paddingRight": 35,
        "paddingLeft": 35,
        "columnGap": 24,
        "showBlockBackground": true,
        "blockInnerWidth": "wide",
        "align": "full",
        "blockBackgroundBackgroundColor": "var(--stk-global-color-40036, #00473d)",
        "showBlockTitle": true,
        "blockTitle": "The Bundles",
        "blockTitleAlign": "center",
        "showBlockDescription": true,
        "blockDescriptionAlign": "center"
    }
}